dswPY/__init__.py
dswPY/info.py
dswPY/tests/__init__.py
dswPY/tests/test_info.py
dswPY-0.0.1.dist-info/LICENSE.txt
dswPY-0.0.1.dist-info/METADATA
dswPY-0.0.1.dist-info/WHEEL
dswPY-0.0.1.dist-info/top_level.txt
dswPY-0.0.1.dist-info/RECORD
